plex_mpv_shim/__init__.py
plex_mpv_shim/action_thread.py
plex_mpv_shim/bulk_subtitle.py
plex_mpv_shim/cli_mgr.py
plex_mpv_shim/client.py
plex_mpv_shim/conf.py
plex_mpv_shim/conffile.py
plex_mpv_shim/gdm.py
plex_mpv_shim/gui_mgr.py
plex_mpv_shim/media.py
plex_mpv_shim/menu.py
plex_mpv_shim/mouse.lua
plex_mpv_shim/mpv_shim.py
plex_mpv_shim/player.py
plex_mpv_shim/subscribers.py
plex_mpv_shim/svp_integration.py
plex_mpv_shim/systray.png
plex_mpv_shim/timeline.py
plex_mpv_shim/utils.py
plex_mpv_shim/video_profile.py
plex_mpv_shim/win_utils.py
plex_mpv_shim/default_shader_pack/LICENSE.md
plex_mpv_shim/default_shader_pack/README.md
plex_mpv_shim/default_shader_pack/pack-hq.json
plex_mpv_shim/default_shader_pack/pack-next.json
plex_mpv_shim/default_shader_pack/pack.json
plex_mpv_shim/default_shader_pack/shaders/Anime4K_AutoDownscalePre_x2.glsl
plex_mpv_shim/default_shader_pack/shaders/Anime4K_AutoDownscalePre_x4.glsl
plex_mpv_shim/default_shader_pack/shaders/Anime4K_Clamp_Highlights.glsl
plex_mpv_shim/default_shader_pack/shaders/Anime4K_Darken_Fast.glsl
plex_mpv_shim/default_shader_pack/shaders/Anime4K_Darken_HQ.glsl
plex_mpv_shim/default_shader_pack/shaders/Anime4K_Darken_VeryFast.glsl
plex_mpv_shim/default_shader_pack/shaders/Anime4K_Deblur_DoG.glsl
plex_mpv_shim/default_shader_pack/shaders/Anime4K_Deblur_Original.glsl
plex_mpv_shim/default_shader_pack/shaders/Anime4K_Denoise_Bilateral_Mean.glsl
plex_mpv_shim/default_shader_pack/shaders/Anime4K_Denoise_Bilateral_Median.glsl
plex_mpv_shim/default_shader_pack/shaders/Anime4K_Denoise_Bilateral_Mode.glsl
plex_mpv_shim/default_shader_pack/shaders/Anime4K_Restore_CNN_L.glsl
plex_mpv_shim/default_shader_pack/shaders/Anime4K_Restore_CNN_M.glsl
plex_mpv_shim/default_shader_pack/shaders/Anime4K_Restore_CNN_S.glsl
plex_mpv_shim/default_shader_pack/shaders/Anime4K_Restore_CNN_Soft_L.glsl
plex_mpv_shim/default_shader_pack/shaders/Anime4K_Restore_CNN_Soft_M.glsl
plex_mpv_shim-1.11.0.dist-info/LICENSE.md
plex_mpv_shim-1.11.0.dist-info/METADATA
plex_mpv_shim-1.11.0.dist-info/WHEEL
plex_mpv_shim-1.11.0.dist-info/entry_points.txt
plex_mpv_shim-1.11.0.dist-info/top_level.txt
plex_mpv_shim-1.11.0.dist-info/RECORD
