Metadata-Version: 2.1
Name: plex-mpv-shim
Version: 1.11.0
Summary: Cast media from Plex Mobile and Web apps to MPV. (Unofficial)
Home-page: https://github.com/iwalton3/plex-mpv-shim
Author: Ian Walton
Author-email: iwalton3@gmail.com
License: MIT
Platform: UNKNOWN
Classifier: Programming Language :: Python :: 3
Classifier: License :: OSI Approved :: MIT License
Classifier: Operating System :: OS Independent
Requires-Python: >=3.6
Requires-Dist: certifi
Requires-Dist: python-mpv
Requires-Dist: python-mpv-jsonipc (>=1.1.8)
Requires-Dist: requests
